{
    "0xfd2487cc0e5dce97f08be1bc8ef1dce8d5988b4d": [
        [
            {
                "full_name": "fallback()",
                "name": "fallback",
                "visibility": "public",
                "payable": false,
                "parameters": {},
                "internalCalls": [
                    "enter"
                ],
                "reads": [],
                "writes": [],
                "randomParameterValues": {}
            },
            {
                "full_name": "fallback()",
                "name": "fallback",
                "visibility": "public",
                "payable": false,
                "parameters": {},
                "internalCalls": [
                    "enter"
                ],
                "reads": [],
                "writes": [],
                "randomParameterValues": {}
            },
            {
                "full_name": "collectFees()",
                "name": "collectFees",
                "visibility": "public",
                "payable": false,
                "parameters": {},
                "internalCalls": [
                    "onlyowner"
                ],
                "reads": [
                    "collectedFees()",
                    "owner()"
                ],
                "writes": [
                    "collectedFees()"
                ],
                "randomParameterValues": {}
            },
            {
                "full_name": "collectFees()",
                "name": "collectFees",
                "visibility": "public",
                "payable": false,
                "parameters": {},
                "internalCalls": [
                    "onlyowner"
                ],
                "reads": [
                    "collectedFees()",
                    "owner()"
                ],
                "writes": [
                    "collectedFees()"
                ],
                "randomParameterValues": {}
            }
        ]
    ]
}